satellite_constellation/Constellation.py
satellite_constellation/ConstellationExceptions.py
satellite_constellation/GroundStation.py
satellite_constellation/Satellite.py
satellite_constellation/SceneCreator.py
satellite_constellation/__init__.py
satellite_constellation/main.py
satellite_constellation/utils.py
satellite_constellation/visualiser.py
satellite_constellation-0.2.2.dist-info/LICENSE
satellite_constellation-0.2.2.dist-info/METADATA
satellite_constellation-0.2.2.dist-info/WHEEL
satellite_constellation-0.2.2.dist-info/entry_points.txt
satellite_constellation-0.2.2.dist-info/top_level.txt
satellite_constellation-0.2.2.dist-info/RECORD
