Metadata-Version: 2.1
Name: satellite-constellation
Version: 0.2.2
Summary: Create Satellite Constellations around the Earth, Luna and planets in the solar system
Home-page: https://gitlab.com/open-galactic/satellite-constellation
Author: Aidan O'Brien - Open Galactic
Author-email: aidan.obrien@opengalactic.com
License: MIT
Keywords: satellite-constellation satellite satellites constellation orbital mechanics
Platform: UNKNOWN
Classifier: Development Status :: 2 - Pre-Alpha
Classifier: License :: OSI Approved :: MIT License
Classifier: Natural Language :: English
Classifier: Programming Language :: Python :: 3
Classifier: Programming Language :: Python :: 3.6
Classifier: Programming Language :: Python :: 3.7
Classifier: Programming Language :: Python :: 3.8
Classifier: Programming Language :: Python :: 3.9
Classifier: Topic :: Scientific/Engineering :: Astronomy
Classifier: Topic :: Scientific/Engineering :: Physics
License-File: LICENSE
